MANIFEST.in
README.rst
setup.cfg
setup.py
ckanext/__init__.py
ckanext/showcase/__init__.py
ckanext/showcase/controller.py
ckanext/showcase/utils.py
ckanext/showcase/views.py
ckanext/showcase/commands/__init__.py
ckanext/showcase/commands/cli.py
ckanext/showcase/commands/paster.py
ckanext/showcase/fanstatic/ckanext_showcase.css
ckanext/showcase/fanstatic/ckeditor-content-style.css
ckanext/showcase/fanstatic/resource.config
ckanext/showcase/fanstatic/webassets.yml
ckanext/showcase/fanstatic/dist/ckeditor.js
ckanext/showcase/fanstatic/js/showcase-ckeditor.js
ckanext/showcase/fanstatic/src/ckeditor.js
ckanext/showcase/i18n/__init__.py
ckanext/showcase/i18n/ckanext-showcase.pot
ckanext/showcase/i18n/de/LC_MESSAGES/ckanext-showcase.mo
ckanext/showcase/i18n/de/LC_MESSAGES/ckanext-showcase.po
ckanext/showcase/i18n/es/LC_MESSAGES/ckanext-showcase.mo
ckanext/showcase/i18n/es/LC_MESSAGES/ckanext-showcase.po
ckanext/showcase/i18n/fr/LC_MESSAGES/ckanext-showcase.mo
ckanext/showcase/i18n/fr/LC_MESSAGES/ckanext-showcase.po
ckanext/showcase/i18n/zh_Hant_TW/LC_MESSAGES/ckanext-showcase.mo
ckanext/showcase/i18n/zh_Hant_TW/LC_MESSAGES/ckanext-showcase.po
ckanext/showcase/logic/__init__.py
ckanext/showcase/logic/auth.py
ckanext/showcase/logic/converters.py
ckanext/showcase/logic/helpers.py
ckanext/showcase/logic/schema.py
ckanext/showcase/logic/validators.py
ckanext/showcase/logic/action/__init__.py
ckanext/showcase/logic/action/create.py
ckanext/showcase/logic/action/delete.py
ckanext/showcase/logic/action/get.py
ckanext/showcase/logic/action/update.py
ckanext/showcase/model/__init__.py
ckanext/showcase/plugin/__init__.py
ckanext/showcase/plugin/flask_plugin.py
ckanext/showcase/plugin/pylons_plugin.py
ckanext/showcase/templates/.gitignore
ckanext/showcase/templates/header.html
ckanext/showcase/templates/admin/confirm_remove_showcase_admin.html
ckanext/showcase/templates/admin/manage_showcase_admins.html
ckanext/showcase/templates/home/snippets/stats.html
ckanext_showcase.egg-info/PKG-INFO
ckanext_showcase.egg-info/SOURCES.txt
ckanext_showcase.egg-info/dependency_links.txt
ckanext_showcase.egg-info/entry_points.txt
ckanext_showcase.egg-info/namespace_packages.txt
ckanext_showcase.egg-info/requires.txt
ckanext_showcase.egg-info/top_level.txt