Metadata-Version: 1.1
Name: ckanext-showcase
Version: 1.5.1
Summary: A ckan extension to showcase datasets in use
Home-page: https://github.com/ckan/ckanext-showcase
Author: Brook Elgie
Author-email: brook.elgie@okfn.org
License: AGPL
Keywords: ckan
Platform: UNKNOWN
Classifier: License :: OSI Approved :: GNU Affero General Public License v3 or later (AGPLv3+)
Classifier: Development Status :: 5 - Production/Stable
Classifier: Programming Language :: Python :: 2.6
Classifier: Programming Language :: Python :: 2.7
